{
    "INDIAN SOCIETY, LITERATURE AND CULTURE": 20,
    "MANUFACTURING & CHARACTERISATION OF POLYMER MATRIX COMPOSITES": 60,
    "SPEAKING AND PRESENTATION": 70,
    "FRENCH": 10,
    "GERMAN": 10,
    "BOUNDARY INTEGRAL METHODS": 40,
    "SCIENCE OF HAPPINESS AND WELL-BEING": 30,
    "MULTI-OBJECTIVE PROGRAMMING": 80,
    "STOCHASTIC PROCESSES": 50,
    "FLUID POWER IN MINING MACHINERY": 30,
    "CLEAN COAL TECHNOLOGY": 20,
    "PRINCIPLES OF MINE PLANNING": 40,
    "SINGLE CRYSTAL X-RAY STRUCTURE ANALYSIS": 50,
    "TRANSPORT IN POROUS MEDIA": 40,
    "SAFETY ANALYTICS": 60,
    "INNOVATION MANAGEMENT": 70,
    "FUEL TECHNOLOGY": 30,
    "GENETIC ALGORITHMS IN ENGINEERING PROCESS MODELING": 60,
    "FINANCING NEW VENTURE": 70,
    "COMPLEX ANALYSIS": 40,
    "ENERGY STORAGE TECHNOLOGIES": 50,
    "MODERN ALGEBRA": 40,
    "WASTE TO WEALTH: MICROBIAL INTERVENTION": 30,
    "COMPUTATIONAL MODELING OF MULTIPHASE REACTIVE FLOWS": 50,
    "PARTIAL DIFFERENTIAL EQUATIONS": 50,
    "INTRODUCTION TO CULTURAL STUDIES": 30,
    "SWITCHING & FINITE AUTOMATA": 40,
    "EDUCATIONAL NEUROSCIENCE": 60,
    "INTEGRAL EQUATIONS AND VARIATIONAL METHODS": 50,
    "REGRESSION & TIME SERIES MODELS": 60,
    "COMPUTATIONAL LINEAR ALGEBRA": 50,
    "FUNDAMENTALS OF BIOENERGY": 40,
    "ADVANCED MASS TRANSFER": 50,
    "PROCESS DYNAMICS & CONTROL": 60,
    "ADVANCED HEAT TRANSFER": 50,
    "COMPUTATIONAL GEOMECHANICS": 50,
    "COAL PREPARATION": 30,
    "ECONOMICS OF ENTREPRENEURSHIP": 60,
    "MANUFACTURING MANAGEMENT": 70,
    "INTRODUCTION TO LANGUAGE AND LINGUISTICS": 20,
    "MANAGEMENT OF GROWTH VENTURES": 70,
    "COMPUTER METHODS IN CHEM. ENGG.": 40,
    "MARKETING AND MARKET RESEARCH": 50,
    "MATERIAL SCIENCE": 50,
    "PETROLEUM AND OCEAN LAW": 20,
    "RUBBER PROCESS ENGINEERING": 40,
    "EDUCATIONAL DATA ANALYTICS": 60,
    "INFORMATION AND COMMUNICATION TECHNOLOGY IN EDUCATION": 60,
    "AUDIO SYSTEMS ENGINEERING": 50,
    "SOFT-COMPUTING TOOLS IN ENGINEERING": 50,
    "TRADE SECRET AND TECHNOLOGY TRANSFER": 50,
    "NON LINEAR PROGRAMMING": 50,
    "STOCHASTIC PROCESS AND SIMULATION": 50,
    "ENVIRONMENTAL SOCIOLOGY": 30,
    "RESEVOIR ENGINEERING FUNDAMENTALS": 40,
    "MEASUREMENT OF HAPPINESS": 30,
    "NETWORKS AND PROJECT MANAGEMENT": 60,
    "FIRE SAFETY ENGINEERING": 40,
    "INTRODUCTION TO FINANCIAL MANAGEMENT": 60,
    "INTRODUCTION TO HUMAN BEHAVIOUR IN ORGANISATION": 50,
    "PETROCHEMICAL TECHNOLOGY": 40,
    "CHEMICAL REACTOR ANALYSIS": 50,
    "METAL COMPLEXES IN CATALYSIS & MATERIAL SCIENCE": 50,
    "STATISTICAL INFERENCE": 50,
    "FOUNDATIONS OF ENTREPRENEURSHIP": 60,
    "NOVEL SEPARATION PROCESSES": 50,
    "DATA STRUCTURE AND ALGORITHM": 50,
    "MOLECULAR SPECTROSCOPY & MOLECULAR STRUCTURE": 50,
    "TRANSFER AND MANAGEMENT OF RURAL TECHNOLOGY": 40,
    "ENVIRONMENTAL HUMANITIES": 30,
    "SANSKRIT AND HERITAGE": 20,
    "LOGISTICS SYSTEMS AND MANAGEMENT": 50,
    "RESERVOIR ENGINEERING FUNDAMENTALS": 40,
    "INTRODUCTION TO INTELLECTUAL PROPERTY LAW": 50,
    "BIODIVERSITY PROTECTION, FARMERS AND BREEDERS RIGHT": 40,
    "SUPRAMOLECULAR CHEMISTRY": 50,
    "STRUCTURE ANALYSIS BY SPECTROSCOPIC & CRYSTALLOGRAPHIC STUDIES": 50,
    "COMPUTER NETWORKS": 50,
    "NEWER ASYMMETRIC REACTIONS": 40,
    "ENGINEERING DESIGN PROCESS": 60,
    "GENERAL PSYCHOLOGY": 50,
    "ENERGY SYSTEMS MODELLING": 50,
    "INTRODUCTION TO SOCIOLOGY": 30,
    "SOLAR PHOTOVOLTAIC TECHNOLOGIES AND SYSTEMS": 50,
    "HYDROCARBON PRODUCTION ENGINEERING": 40,
    "HISTORY OF SCIENCE AND TECHNOLOGY IN ANCIENT INDIA": 30,
    "MEASURE THEORY AND INTEGRATION": 40,
    "OPERATIONS RESEARCH": 60,
    "BOUNDARY ELEMENT METHODS": 40,
    "INTRODUCTION TO GROSS NATIONAL HAPPINESS (GNH)": 30,
    "PATENT DRAFTING AND SPECIFICATION WRITING": 50,
    "INTRODUCTION TO ETHICS": 30,
    "INSTABILITY & PATTERNING IN THIN POLYMER FILM": 40,
    "HAZARDOUS WASTE TREATMENT & MANAGEMENT": 30,
    "SOCIO-TECHNICAL INTERVENTIONS FOR AGEING SOCIETIES": 40,
    "NATURAL GAS ENGINEERING": 40,
    "SPINTRONIC MATERIALS AND DEVICES": 50,
    "HYDROGEN TECHNOLOGY": 40,
    "LANGUAGE PROCESSING FOR E-LEARNING": 50,
    "PROJECT ENGINEERING AND MANAGEMENT": 60
}